{
  "Sawad Candy Box": "Swad Candy.png",
  "Mix Fruit Toffee Jar": "Mix fruit candy.png",
  "Khoya Toffee": "Khoya Toffee Butter.png",
  "Khoya Badam": "khoya.png",
  "Cone Jelly Jar": "Fruit Cone Jelly 10rs.png",
  "Cornoto Cone Chocolate": "corneto cone chocolate.png",
  "Egg Tweet": "Egg Tweet.png",
  "Won Chocolate Paste Jar": "won chocolate paste.png",
  "Shami Meva": "shahi mewa.png",
  "Desi Anda": "Desi Anda.png",
  "Yums": "yumz fruity.png",
  "Fudge Toffee Jar": "Fudge Toffee.png",
  "2 Ever Bunty Sheet": "2ever beans.png",
  "Silk + Bubly Chocolate": "Silk Bubbly Chocolate.png",
  "Daily Milk Chocolate": "Daily Milk Chocolate.png",
  "Spoon Chocolate": "Spoon Chocolate.png",
  "4 Ever Sheet Bunty": "4Ever beans.png",
  "Badam Candy": "badam delight Candy.png",
  "Sorbon Mini Cone Chocolate": "sorbon mini cone chocolate.png",
  "Tim Tim Imli Box": "Tim Tim Imli.png",
  "Usailah Cup Imli": "Tim Tim Imli Imli.png",
  "Lolipop Pop On": "Pop on Loolipop.png",
  "Liquid Chocolate Silk": "silk chocolate.png",
  "Umberala Chocolate": "silky chocolate.png",
  "Sweeto Chocolate Balls": "Sweeto Chocolate Balls.png",
  "Sweeto Chocolate Balls Jar": "Sweeto Chocolate Balls Jar.png",
  "Usailah AnarDana Imli": "Tamarind Imli.png"
}
